SPQR/__init__.py
SPQR/literals.py
spqr-0.0.7.dist-info/LICENSE
spqr-0.0.7.dist-info/WHEEL
spqr-0.0.7.dist-info/METADATA
spqr-0.0.7.dist-info/RECORD
