Metadata-Version: 2.1
Name: SPQR
Version: 0.0.7
Summary: S.P.Q.R
Home-page: https://github.com/Carreau/SPQR
Author: Matthias Bussonnier
Author-email: bussonniermatthias@gmail.com
Requires-Python: >3
Classifier: License :: OSI Approved :: MIT License
Project-URL: Source, https://github.com/Carreau/SPQR
